glm_met/__init__.py
glm_met/glm_met.py
glm_met/nasa_power/__init__.py
glm_met/nasa_power/nasa_power.py
glm_met/nasa_power/settings.py
glm_met/silo/__init__.py
glm_met/silo/settings.py
glm_met/silo/silo.py
glm_met-0.0.7.dist-info/LICENSE
glm_met-0.0.7.dist-info/METADATA
glm_met-0.0.7.dist-info/WHEEL
glm_met-0.0.7.dist-info/top_level.txt
glm_met-0.0.7.dist-info/RECORD
