Metadata-Version: 2.1
Name: glm-met
Version: 0.0.7
Summary: Download meteorological data for the General Lake Model
Author: John Duncan
Project-URL: Homepage, https://wet-tool.github.io/glm-met/
Keywords: GLM,meterological,weather,climate
Classifier: License :: OSI Approved :: MIT License
Classifier: Programming Language :: Python
Classifier: Programming Language :: Python :: 3
Requires-Python: >=3.9
License-File: LICENSE
Requires-Dist: requests
Requires-Dist: pandas
